clkUnit/clkUnit.vhd
library IEEE;
use IEEE.std_logic_1164.all;

entity clkUnit is
  
 port (
   clk, reset : in  std_logic;
   enableTX   : out std_logic;
   enableRX   : out std_logic);
    
end clkUnit;

architecture behavorial of clkUnit is
begin
  enableRX <= clk when reset = '1' else '0';

  process (clk, reset)
    variable cpt : integer;
  begin
    
    if reset = '0' then
      enableTX <= '0';
      cpt := 0;
    elsif rising_edge(clk) then  
      if cpt = 15 then
        enableTX <= '1';
        cpt := 0;
      else 
        enableTX <= '0';
        cpt := cpt + 1;
      end if;
    end if;
  end process;
end behavorial;

TxUnit/TxUnit.vhd
library IEEE;
use IEEE.std_logic_1164.all;

entity TxUnit is
  port (
    clk, reset : in std_logic;
    enable : in std_logic;
    ld : in std_logic;
    txd : out std_logic;
    regE : out std_logic;
    bufE : out std_logic;
    data : in std_logic_vector(7 downto 0));
end TxUnit;



architecture behavorial of TxUnit is
  -- Déclaration du tamppon et du registre d'emission
  signal bufferT, registerT : std_logic_vector(7 downto 0);
  -- Compteur de bit pour savoir si on est dans le cas du bit de start, des 8 bits d'emission, du bit de parité ou du bit de stop 
  signal cpt_bit : integer := 1;

  -- Fonction annexe qui permet de calculer le bit de parité avec comme argument un registre
  function parity_bit(registre : std_logic_vector(7 downto 0)) return std_logic is 
  variable result : std_logic := '0';
  begin
  for i in 0 to 7 loop
    result := result xor registre(i);
  end loop;
  return result;
  end function;

begin
  process(clk,reset)
  begin 
    if reset = '0' then
      cpt_bit <= 0;
      txd <= '1';
      bufE <= '1';
      regE <= '1';

    elsif rising_edge(clk) then 
        if ld = '1' then 
          bufE <= '0';
          bufferT <= data;
          registerT <= bufferT; 
          bufE<='1';
          --Bit de start
          txd <= '0';

        if enable = '1' then
            case cpt_bit is 
                -- Bits de données 
                when 1 to 7 => txd <= registerT(7 - (cpt_bit - 1));
                when 8 =>  txd <= registerT(7 - (cpt_bit - 1));
                           -- Le registre d'émission n'est plus occupé
                           regE <= '1';
                -- Bit de parité calculé avec une fonction annexe
                when 9 => txd <= parity_bit(registerT);
                -- Bit de stop 
                when 10 => txd <= '1';
                          -- On remet le compteur de bit à zéro 
                          cpt_bit <= 1; 
                when others => txd <= '1';
              end case; 
              -- Incrémentation du compteur de bit
              cpt_bit <= cpt_bit + 1;
          end if;
        end if;
    end if;
  end process;
end behavorial;

TxUnit/testTxUnit.vhd
--------------------------------------------------------------------------------
-- Company: 
-- Engineer:
--
-- Create Date:   12:09:49 10/31/2018
-- Design Name:   
-- Module Name:   testTxUnit.vhd
-- Project Name:  uart
-- Target Device:  
-- Tool versions:  
-- Description:   
-- 
-- VHDL Test Bench Created by ISE for module: TxUnit
-- 
-- Dependencies:
-- 
-- Revision:
-- Revision 0.01 - File Created
-- Additional Comments:
--
-- Notes: 
-- This testbench has been automatically generated using types std_logic and
-- std_logic_vector for the ports of the unit under test.  Xilinx recommends
-- that these types always be used for the top-level I/O of a design in order
-- to guarantee that the testbench will bind correctly to the post-implementation 
-- simulation model.
--------------------------------------------------------------------------------
LIBRARY ieee;
USE ieee.std_logic_1164.ALL;
 
-- Uncomment the following library declaration if using
-- arithmetic functions with Signed or Unsigned values
--USE ieee.numeric_std.ALL;
 
ENTITY testTxUnit IS
END testTxUnit;
 
ARCHITECTURE behavior OF testTxUnit IS 
 
    -- Component Declaration for the Unit Under Test (UUT)
 
    COMPONENT TxUnit
    PORT(
         clk : IN  std_logic;
         reset : IN  std_logic;
         enable : IN  std_logic;
         ld : IN  std_logic;
         txd : OUT  std_logic;
         regE : OUT  std_logic;
         bufE : OUT  std_logic;
         data : IN  std_logic_vector(7 downto 0)
        );
    END COMPONENT;
   
    COMPONENT clkUnit
    PORT(
         clk : IN  std_logic;
         reset : IN  std_logic;
         enableTX : OUT  std_logic;
         enableRX : OUT  std_logic
        );
    END COMPONENT;	

   signal clk : std_logic := '0';
   signal reset : std_logic := '0';
   signal enableTx : std_logic := '0';
   signal enableRx : std_logic := '0';
   signal ld : std_logic := '0';
   signal data : std_logic_vector(7 downto 0) := (others => '0');

   signal txd : std_logic;
   signal regE : std_logic;
   signal bufE : std_logic;

   -- Clock period definitions
   constant clk_period : time := 10 ns;
 
BEGIN
 
	-- Instantiate the Unit Under Test
   uut0: TxUnit PORT MAP (
          clk => clk,
          reset => reset,
          enable => enableTX,
          ld => ld,
          txd => txd,
          regE => regE,
          bufE => bufE,
          data => data
        );

   -- Instantiate the clkUnit
   clkUnit1: clkUnit PORT MAP (
          clk => clk,
          reset => reset,
          enableTX => enableTX,
          enableRX => enableRX
        );
		  
   -- Clock process definitions
   clk_process :process
   begin
     clk <= '0';
     wait for clk_period/2;
     clk <= '1';
     wait for clk_period/2;
   end process;
 
 
   -- Stimulus process
   stim_proc: process
   begin		
     -- maintien du reset durant 100 ns.
     wait for 100 ns;	
     reset <= '1';

     wait for 200 ns;

     -- l'émetteur est dispo ?
     if not (regE='1' and bufE='1') then
       wait until regE='1' and bufE='1';
     end if;

     -- si oui, on charge la donnée
     wait for clk_period;
     -- émission du caractère 0x55
     data <= "01010101";
     ld <= '1';

     -- on attend de voir que l'ordre d'émission
     -- a été bien pris en compte avant de rabaisser
     -- le signal ld
     if not (regE='1' and bufE='0') then
       wait until regE='1' and bufE='0';
     end if;
     wait for clk_period;
     ld <= '0';

     -- compléter avec des tests qui montrent que la prise
     -- en compte de la demande d'émission d'un second
     -- caractère se fait lorsqu'on émet un premier caractère
     -- et ceci quelque soit l'étape d'émission
    
     -- si oui, on charge la donnée
     wait for clk_period*190;
     -- émission du caractère 0x55
     data <= "11111111";
     ld <= '1';
     
     -- on attend de voir que l'ordre d'émission
     -- a été bien pris en compte avant de rabaisser
     -- le signal ld
     if not (regE='1' and bufE='0') then
      wait until regE='1' and bufE='0';
    end if;
    wait for clk_period;
    ld <= '0';

    -- si oui, on charge la donnée
    wait for clk_period*100;
    -- émission du caractère 0x55
    data <= "00000001";
    ld <= '1';
    wait for clk_period;
    ld <= '0';

     wait;
   end process;

END;

TxUnit/output.vcd
$date
   Tue Dec 10 11:49:29 2024
$end
$version
  P.20131013
$end
$timescale
  1ps
$end
$scope module testtxunit $end
$var wire 1 Q clk $end
$var wire 1 R reset $end
$var wire 1 S enabletx $end
$var wire 1 T enablerx $end
$var wire 1 4 ld $end
$var wire 1 ? data [7] $end
$var wire 1 > data [6] $end
$var wire 1 = data [5] $end
$var wire 1 < data [4] $end
$var wire 1 ; data [3] $end
$var wire 1 : data [2] $end
$var wire 1 9 data [1] $end
$var wire 1 8 data [0] $end
$var wire 1 5 txd $end
$var wire 1 6 rege $end
$var wire 1 7 bufe $end
$scope module uut0 $end
$var wire 1 Q clk $end
$var wire 1 R reset $end
$var wire 1 S enable $end
$var wire 1 4 ld $end
$var wire 1 5 txd $end
$var wire 1 6 rege $end
$var wire 1 7 bufe $end
$var wire 1 ? data [7] $end
$var wire 1 > data [6] $end
$var wire 1 = data [5] $end
$var wire 1 < data [4] $end
$var wire 1 ; data [3] $end
$var wire 1 : data [2] $end
$var wire 1 9 data [1] $end
$var wire 1 8 data [0] $end
$var wire 1 G buffert [7] $end
$var wire 1 F buffert [6] $end
$var wire 1 E buffert [5] $end
$var wire 1 D buffert [4] $end
$var wire 1 C buffert [3] $end
$var wire 1 B buffert [2] $end
$var wire 1 A buffert [1] $end
$var wire 1 @ buffert [0] $end
$var wire 1 O registert [7] $end
$var wire 1 N registert [6] $end
$var wire 1 M registert [5] $end
$var wire 1 L registert [4] $end
$var wire 1 K registert [3] $end
$var wire 1 J registert [2] $end
$var wire 1 I registert [1] $end
$var wire 1 H registert [0] $end
$upscope $end
$scope module clkUnit1 $end
$var wire 1 Q clk $end
$var wire 1 R reset $end
$var wire 1 S enabletx $end
$var wire 1 T enablerx $end
$upscope $end
$upscope $end
$enddefinitions $end
#0
$dumpvars
0R
0Q
0T
04
0?
0>
0=
0<
0;
0:
09
08
15
16
17
xG
xF
xE
xD
xC
xB
xA
x@
xO
xN
xM
xL
xK
xJ
xI
xH
0S
$end
#5000
1Q
#10000
0Q
#15000
1Q
#20000
0Q
#25000
1Q
#30000
0Q
#35000
1Q
#40000
0Q
#45000
1Q
#50000
0Q
#55000
1Q
#60000
0Q
#65000
1Q
#70000
0Q
#75000
1Q
#80000
0Q
#85000
1Q
#90000
0Q
#95000
1Q
#100000
1R
0Q
#105000
1Q
1T
#110000
0Q
0T
#115000
1Q
1T
#120000
0Q
0T
#125000
1Q
1T
#130000
0Q
0T
#135000
1Q
1T
#140000
0Q
0T
#145000
1Q
1T
#150000
0Q
0T
#155000
1Q
1T
#160000
0Q
0T
#165000
1Q
1T
#170000
0Q
0T
#175000
1Q
1T
#180000
0Q
0T
#185000
1Q
1T
#190000
0Q
0T
#195000
1Q
1T
#200000
0Q
0T
#205000
1Q
1T
#210000
0Q
0T
#215000
1Q
1T
#220000
0Q
0T
#225000
1Q
1T
#230000
0Q
0T
#235000
1Q
1T
#240000
0Q
0T
#245000
1Q
1T
#250000
0Q
0T
#255000
1Q
1T
1S
#260000
0Q
0T
#265000
1Q
1T
0S
#270000
0Q
0T
#275000
1Q
1T
#280000
0Q
0T
#285000
1Q
1T
#290000
0Q
0T
#295000
1Q
1T
#300000
0Q
0T
#305000
1Q
1T
#310000
0Q
0T
14
1>
1<
1:
18
#315000
1Q
1T
05
07
0G
1F
0E
1D
0C
1B
0A
1@
#320000
0Q
0T
#325000
1Q
1T
04
#330000
0Q
0T
#335000
1Q
1T
#340000
0Q
0T
#345000
1Q
1T
#350000
0Q
0T
#355000
1Q
1T
#360000
0Q
0T
#365000
1Q
1T
#370000
0Q
0T
#375000
1Q
1T
#380000
0Q
0T
#385000
1Q
1T
#390000
0Q
0T
#395000
1Q
1T
#400000
0Q
0T
#405000
1Q
1T
#410000
0Q
0T
#415000
1Q
1T
1S
#420000
0Q
0T
#425000
1Q
1T
0S
#430000
0Q
0T
#435000
1Q
1T
#440000
0Q
0T
#445000
1Q
1T
#450000
0Q
0T
#455000
1Q
1T
#460000
0Q
0T
#465000
1Q
1T
#470000
0Q
0T
#475000
1Q
1T
#480000
0Q
0T
#485000
1Q
1T
#490000
0Q
0T
#495000
1Q
1T
#500000
0Q
0T
#505000
1Q
1T
#510000
0Q
0T
#515000
1Q
1T
#520000
0Q
0T
#525000
1Q
1T
#530000
0Q
0T
#535000
1Q
1T
#540000
0Q
0T
#545000
1Q
1T
#550000
0Q
0T
#555000
1Q
1T
#560000
0Q
0T
#565000
1Q
1T
#570000
0Q
0T
#575000
1Q
1T
1S
#580000
0Q
0T
#585000
1Q
1T
0S
#590000
0Q
0T
#595000
1Q
1T
#600000
0Q
0T
#605000
1Q
1T
#610000
0Q
0T
#615000
1Q
1T
#620000
0Q
0T
#625000
1Q
1T
#630000
0Q
0T
#635000
1Q
1T
#640000
0Q
0T
#645000
1Q
1T
#650000
0Q
0T
#655000
1Q
1T
#660000
0Q
0T
#665000
1Q
1T
#670000
0Q
0T
#675000
1Q
1T
#680000
0Q
0T
#685000
1Q
1T
#690000
0Q
0T
#695000
1Q
1T
#700000
0Q
0T
#705000
1Q
1T
#710000
0Q
0T
#715000
1Q
1T
#720000
0Q
0T
#725000
1Q
1T
#730000
0Q
0T
#735000
1Q
1T
1S
#740000
0Q
0T
#745000
1Q
1T
0S
#750000
0Q
0T
#755000
1Q
1T
#760000
0Q
0T
#765000
1Q
1T
#770000
0Q
0T
#775000
1Q
1T
#780000
0Q
0T
#785000
1Q
1T
#790000
0Q
0T
#795000
1Q
1T
#800000
0Q
0T
#805000
1Q
1T
#810000
0Q
0T
#815000
1Q
1T
#820000
0Q
0T
#825000
1Q
1T
#830000
0Q
0T
#835000
1Q
1T
#840000
0Q
0T
#845000
1Q
1T
#850000
0Q
0T
#855000
1Q
1T
#860000
0Q
0T
#865000
1Q
1T
#870000
0Q
0T
#875000
1Q
1T
#880000
0Q
0T
#885000
1Q
1T
#890000
0Q
0T
#895000
1Q
1T
1S
#900000
0Q
0T
#905000
1Q
1T
0S
#910000
0Q
0T
#915000
1Q
1T
#920000
0Q
0T
#925000
1Q
1T
#930000
0Q
0T
#935000
1Q
1T
#940000
0Q
0T
#945000
1Q
1T
#950000
0Q
0T
#955000
1Q
1T
#960000
0Q
0T
#965000
1Q
1T
#970000
0Q
0T
#975000
1Q
1T
#980000
0Q
0T
#985000
1Q
1T
#990000
0Q
0T
#995000
1Q
1T
#1000000
0Q
0T
#1005000
1Q
1T
#1010000
0Q
0T
#1015000
1Q
1T
#1020000
0Q
0T
#1025000
1Q
1T
#1030000
0Q
0T
#1035000
1Q
1T
#1040000
0Q
0T
#1045000
1Q
1T
#1050000
0Q
0T
#1055000
1Q
1T
1S
#1060000
0Q
0T
#1065000
1Q
1T
0S
#1070000
0Q
0T
#1075000
1Q
1T
#1080000
0Q
0T
#1085000
1Q
1T
#1090000
0Q
0T
#1095000
1Q
1T
#1100000
0Q
0T
#1105000
1Q
1T
#1110000
0Q
0T
#1115000
1Q
1T
#1120000
0Q
0T
#1125000
1Q
1T
#1130000
0Q
0T
#1135000
1Q
1T
#1140000
0Q
0T
#1145000
1Q
1T
#1150000
0Q
0T
#1155000
1Q
1T
#1160000
0Q
0T
#1165000
1Q
1T
#1170000
0Q
0T
#1175000
1Q
1T
#1180000
0Q
0T
#1185000
1Q
1T
#1190000
0Q
0T
#1195000
1Q
1T
#1200000
0Q
0T
#1205000
1Q
1T
#1210000
0Q
0T
#1215000
1Q
1T
1S
#1220000
0Q
0T
#1225000
1Q
1T
0S
#1230000
0Q
0T
#1235000
1Q
1T
#1240000
0Q
0T
#1245000
1Q
1T
#1250000
0Q
0T
#1255000
1Q
1T
#1260000
0Q
0T
#1265000
1Q
1T
#1270000
0Q
0T
#1275000
1Q
1T
#1280000
0Q
0T
#1285000
1Q
1T
#1290000
0Q
0T
#1295000
1Q
1T
#1300000
0Q
0T
#1305000
1Q
1T
#1310000
0Q
0T
#1315000
1Q
1T
#1320000
0Q
0T
#1325000
1Q
1T
#1330000
0Q
0T
#1335000
1Q
1T
#1340000
0Q
0T
#1345000
1Q
1T
#1350000
0Q
0T
#1355000
1Q
1T
#1360000
0Q
0T
#1365000
1Q
1T
#1370000
0Q
0T
#1375000
1Q
1T
1S
#1380000
0Q
0T
#1385000
1Q
1T
0S
#1390000
0Q
0T
#1395000
1Q
1T
#1400000
0Q
0T
#1405000
1Q
1T
#1410000
0Q
0T
#1415000
1Q
1T
#1420000
0Q
0T
#1425000
1Q
1T
#1430000
0Q
0T
#1435000
1Q
1T
#1440000
0Q
0T
#1445000
1Q
1T
#1450000
0Q
0T
#1455000
1Q
1T
#1460000
0Q
0T
#1465000
1Q
1T
#1470000
0Q
0T
#1475000
1Q
1T
#1480000
0Q
0T
#1485000
1Q
1T
#1490000
0Q
0T
#1495000
1Q
1T
#1500000
0Q
0T
#1505000
1Q
1T
#1510000
0Q
0T
#1515000
1Q
1T
#1520000
0Q
0T
#1525000
1Q
1T
#1530000
0Q
0T
#1535000
1Q
1T
1S
#1540000
0Q
0T
#1545000
1Q
1T
0S
#1550000
0Q
0T
#1555000
1Q
1T
#1560000
0Q
0T
#1565000
1Q
1T
#1570000
0Q
0T
#1575000
1Q
1T
#1580000
0Q
0T
#1585000
1Q
1T
#1590000
0Q
0T
#1595000
1Q
1T
#1600000
0Q
0T
#1605000
1Q
1T
#1610000
0Q
0T
#1615000
1Q
1T
#1620000
0Q
0T
#1625000
1Q
1T
#1630000
0Q
0T
#1635000
1Q
1T
#1640000
0Q
0T
#1645000
1Q
1T
#1650000
0Q
0T
#1655000
1Q
1T
#1660000
0Q
0T
#1665000
1Q
1T
#1670000
0Q
0T
#1675000
1Q
1T
#1680000
0Q
0T
#1685000
1Q
1T
#1690000
0Q
0T
#1695000
1Q
1T
1S
#1700000
0Q
0T
#1705000
1Q
1T
0S
#1710000
0Q
0T
#1715000
1Q
1T
#1720000
0Q
0T
#1725000
1Q
1T
#1730000
0Q
0T
#1735000
1Q
1T
#1740000
0Q
0T
#1745000
1Q
1T
#1750000
0Q
0T
#1755000
1Q
1T
#1760000
0Q
0T
#1765000
1Q
1T
#1770000
0Q
0T
#1775000
1Q
1T
#1780000
0Q
0T
#1785000
1Q
1T
#1790000
0Q
0T
#1795000
1Q
1T
#1800000
0Q
0T
#1805000
1Q
1T
#1810000
0Q
0T
#1815000
1Q
1T
#1820000
0Q
0T
#1825000
1Q
1T
#1830000
0Q
0T
#1835000
1Q
1T
#1840000
0Q
0T
#1845000
1Q
1T
#1850000
0Q
0T
#1855000
1Q
1T
1S
#1860000
0Q
0T
#1865000
1Q
1T
0S
#1870000
0Q
0T
#1875000
1Q
1T
#1880000
0Q
0T
#1885000
1Q
1T
#1890000
0Q
0T
#1895000
1Q
1T
#1900000
0Q
0T
#1905000
1Q
1T
#1910000
0Q
0T
#1915000
1Q
1T
#1920000
0Q
0T
#1925000
1Q
1T
#1930000
0Q
0T
#1935000
1Q
1T
#1940000
0Q
0T
#1945000
1Q
1T
#1950000
0Q
0T
#1955000
1Q
1T
#1960000
0Q
0T
#1965000
1Q
1T
#1970000
0Q
0T
#1975000
1Q
1T
#1980000
0Q
0T
#1985000
1Q
1T
#1990000
0Q
0T
#1995000
1Q
1T
#2000000
0Q
0T
#2005000
1Q
1T
#2010000
0Q
0T
#2015000
1Q
1T
1S
#2020000
0Q
0T
#2025000
1Q
1T
0S
#2030000
0Q
0T
#2035000
1Q
1T
#2040000
0Q
0T
#2045000
1Q
1T
#2050000
0Q
0T
#2055000
1Q
1T
#2060000
0Q
0T
#2065000
1Q
1T
#2070000
0Q
0T
#2075000
1Q
1T
#2080000
0Q
0T
#2085000
1Q
1T
#2090000
0Q
0T
#2095000
1Q
1T
#2100000
0Q
0T
#2105000
1Q
1T
#2110000
0Q
0T
#2115000
1Q
1T
#2120000
0Q
0T
#2125000
1Q
1T
#2130000
0Q
0T
#2135000
1Q
1T
#2140000
0Q
0T
#2145000
1Q
1T
#2150000
0Q
0T
#2155000
1Q
1T
#2160000
0Q
0T
#2165000
1Q
1T
#2170000
0Q
0T
#2175000
1Q
1T
1S
#2180000
0Q
0T
#2185000
1Q
1T
0S
#2190000
0Q
0T
#2195000
1Q
1T
#2200000
0Q
0T
#2205000
1Q
1T
#2210000
0Q
0T
#2215000
1Q
1T
#2220000
0Q
0T
#2225000
1Q
1T
#2230000
0Q
0T
#2235000
1Q
1T
#2240000
0Q
0T
#2245000
1Q
1T
#2250000
0Q
0T
#2255000
1Q
1T
#2260000
0Q
0T
#2265000
1Q
1T
#2270000
0Q
0T
#2275000
1Q
1T
#2280000
0Q
0T
#2285000
1Q
1T
#2290000
0Q
0T
#2295000
1Q
1T
#2300000
0Q
0T
#2305000
1Q
1T
#2310000
0Q
0T
#2315000
1Q
1T
#2320000
0Q
0T
#2325000
1Q
1T
#2330000
0Q
0T
#2335000
1Q
1T
1S
#2340000
0Q
0T
#2345000
1Q
1T
0S
#2350000
0Q
0T
#2355000
1Q
1T
#2360000
0Q
0T
#2365000
1Q
1T
#2370000
0Q
0T
#2375000
1Q
1T
#2380000
0Q
0T
#2385000
1Q
1T
#2390000
0Q
0T
#2395000
1Q
1T
#2400000
0Q
0T
#2405000
1Q
1T
#2410000
0Q
0T
#2415000
1Q
1T
#2420000
0Q
0T
#2425000
1Q
1T
#2430000
0Q
0T
#2435000
1Q
1T
#2440000
0Q
0T
#2445000
1Q
1T
#2450000
0Q
0T
#2455000
1Q
1T
#2460000
0Q
0T
#2465000
1Q
1T
#2470000
0Q
0T
#2475000
1Q
1T
#2480000
0Q
0T
#2485000
1Q
1T
#2490000
0Q
0T
#2495000
1Q
1T
1S
#2500000
0Q
0T
#2505000
1Q
1T
0S
#2510000
0Q
0T
#2515000
1Q
1T
#2520000
0Q
0T
#2525000
1Q
1T
#2530000
0Q
0T
#2535000
1Q
1T
#2540000
0Q
0T
#2545000
1Q
1T
#2550000
0Q
0T
#2555000
1Q
1T
#2560000
0Q
0T
#2565000
1Q
1T
#2570000
0Q
0T
#2575000
1Q
1T
#2580000
0Q
0T
#2585000
1Q
1T
#2590000
0Q
0T
#2595000
1Q
1T
#2600000
0Q
0T
#2605000
1Q
1T
#2610000
0Q
0T
#2615000
1Q
1T
#2620000
0Q
0T
#2625000
1Q
1T
#2630000
0Q
0T
#2635000
1Q
1T
#2640000
0Q
0T
#2645000
1Q
1T
#2650000
0Q
0T
#2655000
1Q
1T
1S
#2660000
0Q
0T
#2665000
1Q
1T
0S
#2670000
0Q
0T
#2675000
1Q
1T
#2680000
0Q
0T
#2685000
1Q
1T
#2690000
0Q
0T
#2695000
1Q
1T
#2700000
0Q
0T
#2705000
1Q
1T
#2710000
0Q
0T
#2715000
1Q
1T
#2720000
0Q
0T
#2725000
1Q
1T
#2730000
0Q
0T
#2735000
1Q
1T
#2740000
0Q
0T
#2745000
1Q
1T
#2750000
0Q
0T
#2755000
1Q
1T
#2760000
0Q
0T
#2765000
1Q
1T
#2770000
0Q
0T
#2775000
1Q
1T
#2780000
0Q
0T
#2785000
1Q
1T
#2790000
0Q
0T
#2795000
1Q
1T
#2800000
0Q
0T
#2805000
1Q
1T
#2810000
0Q
0T
#2815000
1Q
1T
1S
#2820000
0Q
0T
#2825000
1Q
1T
0S
#2830000
0Q
0T
#2835000
1Q
1T
#2840000
0Q
0T
#2845000
1Q
1T
#2850000
0Q
0T
#2855000
1Q
1T
#2860000
0Q
0T
#2865000
1Q
1T
#2870000
0Q
0T
#2875000
1Q
1T
#2880000
0Q
0T
#2885000
1Q
1T
#2890000
0Q
0T
#2895000
1Q
1T
#2900000
0Q
0T
#2905000
1Q
1T
#2910000
0Q
0T
#2915000
1Q
1T
#2920000
0Q
0T
#2925000
1Q
1T
#2930000
0Q
0T
#2935000
1Q
1T
#2940000
0Q
0T
#2945000
1Q
1T
#2950000
0Q
0T
#2955000
1Q
1T
#2960000
0Q
0T
#2965000
1Q
1T
#2970000
0Q
0T
#2975000
1Q
1T
1S
#2980000
0Q
0T
#2985000
1Q
1T
0S
#2990000
0Q
0T
#2995000
1Q
1T
#3000000
0Q
0T
#3005000
1Q
1T
#3010000
0Q
0T
#3015000
1Q
1T
#3020000
0Q
0T
#3025000
1Q
1T
#3030000
0Q
0T
#3035000
1Q
1T
#3040000
0Q
0T
#3045000
1Q
1T
#3050000
0Q
0T
#3055000
1Q
1T
#3060000
0Q
0T
#3065000
1Q
1T
#3070000
0Q
0T
#3075000
1Q
1T
#3080000
0Q
0T
#3085000
1Q
1T
#3090000
0Q
0T
#3095000
1Q
1T
#3100000
0Q
0T
#3105000
1Q
1T
#3110000
0Q
0T
#3115000
1Q
1T
#3120000
0Q
0T
#3125000
1Q
1T
#3130000
0Q
0T
#3135000
1Q
1T
1S
#3140000
0Q
0T
#3145000
1Q
1T
0S
#3150000
0Q
0T
#3155000
1Q
1T
#3160000
0Q
0T
#3165000
1Q
1T
#3170000
0Q
0T
#3175000
1Q
1T
#3180000
0Q
0T
#3185000
1Q
1T
#3190000
0Q
0T
#3195000
1Q
1T
#3200000
0Q
0T
#3205000
1Q
1T
#3210000
0Q
0T
#3215000
1Q
1T
#3220000
0Q
0T
#3225000
1Q
1T
#3230000
0Q
0T
#3235000
1Q
1T
#3240000
0Q
0T
#3245000
1Q
1T
#3250000
0Q
0T
#3255000
1Q
1T
#3260000
0Q
0T
#3265000
1Q
1T
#3270000
0Q
0T
#3275000
1Q
1T
#3280000
0Q
0T
#3285000
1Q
1T
#3290000
0Q
0T
#3295000
1Q
1T
1S
#3300000
0Q
0T
#3305000
1Q
1T
0S
#3310000
0Q
0T
#3315000
1Q
1T
#3320000
0Q
0T
#3325000
1Q
1T
#3330000
0Q
0T
#3335000
1Q
1T
#3340000
0Q
0T
#3345000
1Q
1T
#3350000
0Q
0T
#3355000
1Q
1T
#3360000
0Q
0T
#3365000
1Q
1T
#3370000
0Q
0T
#3375000
1Q
1T
#3380000
0Q
0T
#3385000
1Q
1T
#3390000
0Q
0T
#3395000
1Q
1T
#3400000
0Q
0T
#3405000
1Q
1T
#3410000
0Q
0T
#3415000
1Q
1T
#3420000
0Q
0T
#3425000
1Q
1T
#3430000
0Q
0T
#3435000
1Q
1T
#3440000
0Q
0T
#3445000
1Q
1T
#3450000
0Q
0T
#3455000
1Q
1T
1S
#3460000
0Q
0T
#3465000
1Q
1T
0S
#3470000
0Q
0T
#3475000
1Q
1T
#3480000
0Q
0T
#3485000
1Q
1T
#3490000
0Q
0T
#3495000
1Q
1T
#3500000
0Q
0T
#3505000
1Q
1T
#3510000
0Q
0T
#3515000
1Q
1T
#3520000
0Q
0T
#3525000
1Q
1T
#3530000
0Q
0T
#3535000
1Q
1T
#3540000
0Q
0T
#3545000
1Q
1T
#3550000
0Q
0T
#3555000
1Q
1T
#3560000
0Q
0T
#3565000
1Q
1T
#3570000
0Q
0T
#3575000
1Q
1T
#3580000
0Q
0T
#3585000
1Q
1T
#3590000
0Q
0T
#3595000
1Q
1T
#3600000
0Q
0T
#3605000
1Q
1T
#3610000
0Q
0T
#3615000
1Q
1T
1S
#3620000
0Q
0T
#3625000
1Q
1T
0S
#3630000
0Q
0T
#3635000
1Q
1T
#3640000
0Q
0T
#3645000
1Q
1T
#3650000
0Q
0T
#3655000
1Q
1T
#3660000
0Q
0T
#3665000
1Q
1T
#3670000
0Q
0T
#3675000
1Q
1T
#3680000
0Q
0T
#3685000
1Q
1T
#3690000
0Q
0T
#3695000
1Q
1T
#3700000
0Q
0T
#3705000
1Q
1T
#3710000
0Q
0T
#3715000
1Q
1T
#3720000
0Q
0T
#3725000
1Q
1T
#3730000
0Q
0T
#3735000
1Q
1T
#3740000
0Q
0T
#3745000
1Q
1T
#3750000
0Q
0T
#3755000
1Q
1T
#3760000
0Q
0T
#3765000
1Q
1T
#3770000
0Q
0T
#3775000
1Q
1T
1S
#3780000
0Q
0T
#3785000
1Q
1T
0S
#3790000
0Q
0T
#3795000
1Q
1T
#3800000
0Q
0T
#3805000
1Q
1T
#3810000
0Q
0T
#3815000
1Q
1T
#3820000
0Q
0T
#3825000
1Q
1T
#3830000
0Q
0T
#3835000
1Q
1T
#3840000
0Q
0T
#3845000
1Q
1T
#3850000
0Q
0T
#3855000
1Q
1T
#3860000
0Q
0T
#3865000
1Q
1T
#3870000
0Q
0T
#3875000
1Q
1T
#3880000
0Q
0T
#3885000
1Q
1T
#3890000
0Q
0T
#3895000
1Q
1T
#3900000
0Q
0T
#3905000
1Q
1T
#3910000
0Q
0T
#3915000
1Q
1T
#3920000
0Q
0T
#3925000
1Q
1T
#3930000
0Q
0T
#3935000
1Q
1T
1S
#3940000
0Q
0T
#3945000
1Q
1T
0S
#3950000
0Q
0T
#3955000
1Q
1T
#3960000
0Q
0T
#3965000
1Q
1T
#3970000
0Q
0T
#3975000
1Q
1T
#3980000
0Q
0T
#3985000
1Q
1T
#3990000
0Q
0T
#3995000
1Q
1T
#4000000
0Q
0T
