clkUnit/clkUnit.vhd
library IEEE;
use IEEE.std_logic_1164.all;

entity clkUnit is
  
 port (
   clk, reset : in  std_logic;
   enableTX   : out std_logic;
   enableRX   : out std_logic);
    
end clkUnit;

architecture behavorial of clkUnit is
begin
  enableRX <= clk when reset = '1' else '0';

  process (clk, reset)
    variable cpt : integer;
  begin
    
    if reset = '0' then
      enableTX <= '0';
      cpt := 0;
    elsif rising_edge(clk) then  
      if cpt = 15 then
        enableTX <= '1';
        cpt := 0;
      else 
        enableTX <= '0';
        cpt := cpt + 1;
      end if;
    end if;
  end process;
end behavorial;

TxUnit/TxUnit.vhd
library IEEE;
use IEEE.std_logic_1164.all;

entity TxUnit is
  port (
    clk, reset : in std_logic;
    enable : in std_logic;
    ld : in std_logic;
    txd : out std_logic;
    regE : out std_logic;
    bufE : out std_logic;
    data : in std_logic_vector(7 downto 0));
end TxUnit;



architecture behavorial of TxUnit is
  -- Déclaration du tamppon et du registre d'emission
  signal bufferT, registerT : std_logic_vector(7 downto 0);
  
  signal bufE_signal : std_logic;
  -- Parité
  signal parite : std_logic := '0';
  --etat
  type t_etat is (repos,init,debut,transmission,fin);
  signal etat : t_etat;

begin

  bufE <= bufE_signal;
  process(clk,reset)
  -- Compteur de bit pour savoir si on est dans le cas du bit de start, des 8 bits d'emission, du bit de parité ou du bit de stop 
  variable cpt_bit : integer;
  begin 
    if reset = '0' then
      cpt_bit := 8;
      txd <= '1';
      bufE_signal <= '1';
      etat <= repos;
      regE <= '1';
      parite <= '1';

    elsif rising_edge(clk) then 
        case etat is 

          when repos => 
            if ld = '1' then 
              etat <= init;          
            end if;

          when init => 
            registerT <= bufferT;
            regE <= '0';
            bufE_signal <= '1';
            etat <= debut;
            parite <= '1';

          when debut => 
            if enable = '1' then
              txd <= '0';
              cpt_bit := 8;
              etat <= transmission;
            end if;

          when transmission => 
            
            if enable = '1' and cpt_bit > 0 then
              cpt_bit := cpt_bit - 1;
              txd <= registerT(cpt_bit);
              parite <= parite xor registerT(cpt_bit);
            elsif enable = '1' and cpt_bit = 0 then
              txd <= parite;
              etat <= fin;
            end if;

          when fin => 

            if enable = '1' then
              txd <= '1';
              if bufE_signal = '0' then
                etat <= init;
              elsif bufE_signal = '1' then
                etat <= repos;
              end if;
            end if;
            regE <= '1';
      end case;

      if ld = '1' then
        bufferT <= data;
        bufE_signal <= '0';
      end if;
    end if;
  end process;
end behavorial;

TxUnit/testTxUnit.vhd
--------------------------------------------------------------------------------
-- Company: 
-- Engineer:
--
-- Create Date:   12:09:49 10/31/2018
-- Design Name:   
-- Module Name:   testTxUnit.vhd
-- Project Name:  uart
-- Target Device:  
-- Tool versions:  
-- Description:   
-- 
-- VHDL Test Bench Created by ISE for module: TxUnit
-- 
-- Dependencies:
-- 
-- Revision:
-- Revision 0.01 - File Created
-- Additional Comments:
--
-- Notes: 
-- This testbench has been automatically generated using types std_logic and
-- std_logic_vector for the ports of the unit under test.  Xilinx recommends
-- that these types always be used for the top-level I/O of a design in order
-- to guarantee that the testbench will bind correctly to the post-implementation 
-- simulation model.
--------------------------------------------------------------------------------
LIBRARY ieee;
USE ieee.std_logic_1164.ALL;
 
-- Uncomment the following library declaration if using
-- arithmetic functions with Signed or Unsigned values
--USE ieee.numeric_std.ALL;
 
ENTITY testTxUnit IS
END testTxUnit;
 
ARCHITECTURE behavior OF testTxUnit IS 
 
    -- Component Declaration for the Unit Under Test (UUT)
 
    COMPONENT TxUnit
    PORT(
         clk : IN  std_logic;
         reset : IN  std_logic;
         enable : IN  std_logic;
         ld : IN  std_logic;
         txd : OUT  std_logic;
         regE : OUT  std_logic;
         bufE : OUT  std_logic;
         data : IN  std_logic_vector(7 downto 0)
        );
    END COMPONENT;
   
    COMPONENT clkUnit
    PORT(
         clk : IN  std_logic;
         reset : IN  std_logic;
         enableTX : OUT  std_logic;
         enableRX : OUT  std_logic
        );
    END COMPONENT;	

   signal clk : std_logic := '0';
   signal reset : std_logic := '0';
   signal enableTx : std_logic := '0';
   signal enableRx : std_logic := '0';
   signal ld : std_logic := '0';
   signal data : std_logic_vector(7 downto 0) := (others => '0');

   signal txd : std_logic;
   signal regE : std_logic;
   signal bufE : std_logic;

   -- Clock period definitions
   constant clk_period : time := 10 ns;
 
BEGIN
 
	-- Instantiate the Unit Under Test
   uut0: TxUnit PORT MAP (
          clk => clk,
          reset => reset,
          enable => enableTX,
          ld => ld,
          txd => txd,
          regE => regE,
          bufE => bufE,
          data => data
        );

   -- Instantiate the clkUnit
   clkUnit1: clkUnit PORT MAP (
          clk => clk,
          reset => reset,
          enableTX => enableTX,
          enableRX => enableRX
        );
		  
   -- Clock process definitions
   clk_process :process
   begin
     clk <= '0';
     wait for clk_period/2;
     clk <= '1';
     wait for clk_period/2;
   end process;
 
 
   -- Stimulus process
   stim_proc: process
   begin		
     -- maintien du reset durant 100 ns.
     wait for 100 ns;	
     reset <= '1';

     wait for 200 ns;

     -- l'émetteur est dispo ?
     if not (regE='1' and bufE='1') then
       wait until regE='1' and bufE='1';
     end if;

     -- si oui, on charge la donnée
     wait for clk_period;
     -- émission du caractère 0x55
     data <= "01010101";
     ld <= '1';

     -- on attend de voir que l'ordre d'émission
     -- a été bien pris en compte avant de rabaisser
     -- le signal ld
     if not (regE='1' and bufE='0') then
       wait until regE='1' and bufE='0';
     end if;
     wait for clk_period;
     ld <= '0';

     -- compléter avec des tests qui montrent que la prise
     -- en compte de la demande d'émission d'un second
     -- caractère se fait lorsqu'on émet un premier caractère
     -- et ceci quelque soit l'étape d'émission
    
     -- si oui, on charge la donnée
     wait for clk_period*190;
     -- émission du caractère 0x55
     data <= "11111111";
     ld <= '1';
     
     -- on attend de voir que l'ordre d'émission
     -- a été bien pris en compte avant de rabaisser
     -- le signal ld
     if not (regE='1' and bufE='0') then
      wait until regE='1' and bufE='0';
    end if;
    wait for clk_period;
    ld <= '0';

    -- si oui, on charge la donnée
    wait for clk_period*100;
    -- émission du caractère 0x55
    data <= "00000001";
    ld <= '1';
    wait for clk_period;
    ld <= '0';

     wait;
   end process;

END;

TxUnit/output.vcd
$date
   Tue Dec 17 15:24:13 2024
$end
$version
  P.20131013
$end
$timescale
  1ps
$end
$scope module testtxunit $end
$var wire 1 S clk $end
$var wire 1 T reset $end
$var wire 1 U enabletx $end
$var wire 1 V enablerx $end
$var wire 1 4 ld $end
$var wire 1 ? data [7] $end
$var wire 1 > data [6] $end
$var wire 1 = data [5] $end
$var wire 1 < data [4] $end
$var wire 1 ; data [3] $end
$var wire 1 : data [2] $end
$var wire 1 9 data [1] $end
$var wire 1 8 data [0] $end
$var wire 1 5 txd $end
$var wire 1 6 rege $end
$var wire 1 7 bufe $end
$scope module uut0 $end
$var wire 1 S clk $end
$var wire 1 T reset $end
$var wire 1 U enable $end
$var wire 1 4 ld $end
$var wire 1 5 txd $end
$var wire 1 6 rege $end
$var wire 1 7 bufe $end
$var wire 1 ? data [7] $end
$var wire 1 > data [6] $end
$var wire 1 = data [5] $end
$var wire 1 < data [4] $end
$var wire 1 ; data [3] $end
$var wire 1 : data [2] $end
$var wire 1 9 data [1] $end
$var wire 1 8 data [0] $end
$var wire 1 G buffert [7] $end
$var wire 1 F buffert [6] $end
$var wire 1 E buffert [5] $end
$var wire 1 D buffert [4] $end
$var wire 1 C buffert [3] $end
$var wire 1 B buffert [2] $end
$var wire 1 A buffert [1] $end
$var wire 1 @ buffert [0] $end
$var wire 1 O registert [7] $end
$var wire 1 N registert [6] $end
$var wire 1 M registert [5] $end
$var wire 1 L registert [4] $end
$var wire 1 K registert [3] $end
$var wire 1 J registert [2] $end
$var wire 1 I registert [1] $end
$var wire 1 H registert [0] $end
$var wire 1 P bufe_signal $end
$var wire 1 Q parite $end
$upscope $end
$scope module clkUnit1 $end
$var wire 1 S clk $end
$var wire 1 T reset $end
$var wire 1 U enabletx $end
$var wire 1 V enablerx $end
$upscope $end
$upscope $end
$enddefinitions $end
#0
$dumpvars
0T
0S
0U
0V
04
0?
0>
0=
0<
0;
0:
09
08
15
16
17
xG
xF
xE
xD
xC
xB
xA
x@
xO
xN
xM
xL
xK
xJ
xI
xH
1P
1Q
$end
#5000
1S
#10000
0S
#15000
1S
#20000
0S
#25000
1S
#30000
0S
#35000
1S
#40000
0S
#45000
1S
#50000
0S
#55000
1S
#60000
0S
#65000
1S
#70000
0S
#75000
1S
#80000
0S
#85000
1S
#90000
0S
#95000
1S
#100000
1T
0S
#105000
1S
1V
#110000
0S
0V
#115000
1S
1V
#120000
0S
0V
#125000
1S
1V
#130000
0S
0V
#135000
1S
1V
#140000
0S
0V
#145000
1S
1V
#150000
0S
0V
#155000
1S
1V
#160000
0S
0V
#165000
1S
1V
#170000
0S
0V
#175000
1S
1V
#180000
0S
0V
#185000
1S
1V
#190000
0S
0V
#195000
1S
1V
#200000
0S
0V
#205000
1S
1V
#210000
0S
0V
#215000
1S
1V
#220000
0S
0V
#225000
1S
1V
#230000
0S
0V
#235000
1S
1V
#240000
0S
0V
#245000
1S
1V
#250000
0S
0V
#255000
1S
1U
1V
#260000
0S
0V
#265000
1S
0U
1V
#270000
0S
0V
#275000
1S
1V
#280000
0S
0V
#285000
1S
1V
#290000
0S
0V
#295000
1S
1V
#300000
0S
0V
#305000
1S
1V
#310000
0S
0V
14
1>
1<
1:
18
#315000
1S
1V
07
0G
1F
0E
1D
0C
1B
0A
1@
0P
#320000
0S
0V
#325000
1S
1V
04
06
17
0O
1N
0M
1L
0K
1J
0I
1H
1P
#330000
0S
0V
#335000
1S
1V
#340000
0S
0V
#345000
1S
1V
#350000
0S
0V
#355000
1S
1V
#360000
0S
0V
#365000
1S
1V
#370000
0S
0V
#375000
1S
1V
#380000
0S
0V
#385000
1S
1V
#390000
0S
0V
#395000
1S
1V
#400000
0S
0V
#405000
1S
1V
#410000
0S
0V
#415000
1S
1U
1V
#420000
0S
0V
#425000
1S
0U
1V
05
#430000
0S
0V
#435000
1S
1V
#440000
0S
0V
#445000
1S
1V
#450000
0S
0V
#455000
1S
1V
#460000
0S
0V
#465000
1S
1V
#470000
0S
0V
#475000
1S
1V
#480000
0S
0V
#485000
1S
1V
#490000
0S
0V
#495000
1S
1V
#500000
0S
0V
#505000
1S
1V
#510000
0S
0V
#515000
1S
1V
#520000
0S
0V
#525000
1S
1V
#530000
0S
0V
#535000
1S
1V
#540000
0S
0V
#545000
1S
1V
#550000
0S
0V
#555000
1S
1V
#560000
0S
0V
#565000
1S
1V
#570000
0S
0V
#575000
1S
1U
1V
#580000
0S
0V
#585000
1S
0U
1V
#590000
0S
0V
#595000
1S
1V
#600000
0S
0V
#605000
1S
1V
#610000
0S
0V
#615000
1S
1V
#620000
0S
0V
#625000
1S
1V
#630000
0S
0V
#635000
1S
1V
#640000
0S
0V
#645000
1S
1V
#650000
0S
0V
#655000
1S
1V
#660000
0S
0V
#665000
1S
1V
#670000
0S
0V
#675000
1S
1V
#680000
0S
0V
#685000
1S
1V
#690000
0S
0V
#695000
1S
1V
#700000
0S
0V
#705000
1S
1V
#710000
0S
0V
#715000
1S
1V
#720000
0S
0V
#725000
1S
1V
#730000
0S
0V
#735000
1S
1U
1V
#740000
0S
0V
#745000
1S
0U
1V
15
0Q
#750000
0S
0V
#755000
1S
1V
#760000
0S
0V
#765000
1S
1V
#770000
0S
0V
#775000
1S
1V
#780000
0S
0V
#785000
1S
1V
#790000
0S
0V
#795000
1S
1V
#800000
0S
0V
#805000
1S
1V
#810000
0S
0V
#815000
1S
1V
#820000
0S
0V
#825000
1S
1V
#830000
0S
0V
#835000
1S
1V
#840000
0S
0V
#845000
1S
1V
#850000
0S
0V
#855000
1S
1V
#860000
0S
0V
#865000
1S
1V
#870000
0S
0V
#875000
1S
1V
#880000
0S
0V
#885000
1S
1V
#890000
0S
0V
#895000
1S
1U
1V
#900000
0S
0V
#905000
1S
0U
1V
05
#910000
0S
0V
#915000
1S
1V
#920000
0S
0V
#925000
1S
1V
#930000
0S
0V
#935000
1S
1V
#940000
0S
0V
#945000
1S
1V
#950000
0S
0V
#955000
1S
1V
#960000
0S
0V
#965000
1S
1V
#970000
0S
0V
#975000
1S
1V
#980000
0S
0V
#985000
1S
1V
#990000
0S
0V
#995000
1S
1V
#1000000
0S
0V
#1005000
1S
1V
#1010000
0S
0V
#1015000
1S
1V
#1020000
0S
0V
#1025000
1S
1V
#1030000
0S
0V
#1035000
1S
1V
#1040000
0S
0V
#1045000
1S
1V
#1050000
0S
0V
#1055000
1S
1U
1V
#1060000
0S
0V
#1065000
1S
0U
1V
15
1Q
#1070000
0S
0V
#1075000
1S
1V
#1080000
0S
0V
#1085000
1S
1V
#1090000
0S
0V
#1095000
1S
1V
#1100000
0S
0V
#1105000
1S
1V
#1110000
0S
0V
#1115000
1S
1V
#1120000
0S
0V
#1125000
1S
1V
#1130000
0S
0V
#1135000
1S
1V
#1140000
0S
0V
#1145000
1S
1V
#1150000
0S
0V
#1155000
1S
1V
#1160000
0S
0V
#1165000
1S
1V
#1170000
0S
0V
#1175000
1S
1V
#1180000
0S
0V
#1185000
1S
1V
#1190000
0S
0V
#1195000
1S
1V
#1200000
0S
0V
#1205000
1S
1V
#1210000
0S
0V
#1215000
1S
1U
1V
#1220000
0S
0V
#1225000
1S
0U
1V
05
#1230000
0S
0V
#1235000
1S
1V
#1240000
0S
0V
#1245000
1S
1V
#1250000
0S
0V
#1255000
1S
1V
#1260000
0S
0V
#1265000
1S
1V
#1270000
0S
0V
#1275000
1S
1V
#1280000
0S
0V
#1285000
1S
1V
#1290000
0S
0V
#1295000
1S
1V
#1300000
0S
0V
#1305000
1S
1V
#1310000
0S
0V
#1315000
1S
1V
#1320000
0S
0V
#1325000
1S
1V
#1330000
0S
0V
#1335000
1S
1V
#1340000
0S
0V
#1345000
1S
1V
#1350000
0S
0V
#1355000
1S
1V
#1360000
0S
0V
#1365000
1S
1V
#1370000
0S
0V
#1375000
1S
1U
1V
#1380000
0S
0V
#1385000
1S
0U
1V
15
0Q
#1390000
0S
0V
#1395000
1S
1V
#1400000
0S
0V
#1405000
1S
1V
#1410000
0S
0V
#1415000
1S
1V
#1420000
0S
0V
#1425000
1S
1V
#1430000
0S
0V
#1435000
1S
1V
#1440000
0S
0V
#1445000
1S
1V
#1450000
0S
0V
#1455000
1S
1V
#1460000
0S
0V
#1465000
1S
1V
#1470000
0S
0V
#1475000
1S
1V
#1480000
0S
0V
#1485000
1S
1V
#1490000
0S
0V
#1495000
1S
1V
#1500000
0S
0V
#1505000
1S
1V
#1510000
0S
0V
#1515000
1S
1V
#1520000
0S
0V
#1525000
1S
1V
#1530000
0S
0V
#1535000
1S
1U
1V
#1540000
0S
0V
#1545000
1S
0U
1V
05
#1550000
0S
0V
#1555000
1S
1V
#1560000
0S
0V
#1565000
1S
1V
#1570000
0S
0V
#1575000
1S
1V
#1580000
0S
0V
#1585000
1S
1V
#1590000
0S
0V
#1595000
1S
1V
#1600000
0S
0V
#1605000
1S
1V
#1610000
0S
0V
#1615000
1S
1V
#1620000
0S
0V
#1625000
1S
1V
#1630000
0S
0V
#1635000
1S
1V
#1640000
0S
0V
#1645000
1S
1V
#1650000
0S
0V
#1655000
1S
1V
#1660000
0S
0V
#1665000
1S
1V
#1670000
0S
0V
#1675000
1S
1V
#1680000
0S
0V
#1685000
1S
1V
#1690000
0S
0V
#1695000
1S
1U
1V
#1700000
0S
0V
#1705000
1S
0U
1V
15
1Q
#1710000
0S
0V
#1715000
1S
1V
#1720000
0S
0V
#1725000
1S
1V
#1730000
0S
0V
#1735000
1S
1V
#1740000
0S
0V
#1745000
1S
1V
#1750000
0S
0V
#1755000
1S
1V
#1760000
0S
0V
#1765000
1S
1V
#1770000
0S
0V
#1775000
1S
1V
#1780000
0S
0V
#1785000
1S
1V
#1790000
0S
0V
#1795000
1S
1V
#1800000
0S
0V
#1805000
1S
1V
#1810000
0S
0V
#1815000
1S
1V
#1820000
0S
0V
#1825000
1S
1V
#1830000
0S
0V
#1835000
1S
1V
#1840000
0S
0V
#1845000
1S
1V
#1850000
0S
0V
#1855000
1S
1U
1V
#1860000
0S
0V
#1865000
1S
0U
1V
#1870000
0S
0V
#1875000
1S
1V
16
#1880000
0S
0V
#1885000
1S
1V
#1890000
0S
0V
#1895000
1S
1V
#1900000
0S
0V
#1905000
1S
1V
#1910000
0S
0V
#1915000
1S
1V
#1920000
0S
0V
#1925000
1S
1V
#1930000
0S
0V
#1935000
1S
1V
#1940000
0S
0V
#1945000
1S
1V
#1950000
0S
0V
#1955000
1S
1V
#1960000
0S
0V
#1965000
1S
1V
#1970000
0S
0V
#1975000
1S
1V
#1980000
0S
0V
#1985000
1S
1V
#1990000
0S
0V
#1995000
1S
1V
#2000000
0S
0V
#2005000
1S
1V
#2010000
0S
0V
#2015000
1S
1U
1V
#2020000
0S
0V
#2025000
1S
0U
1V
#2030000
0S
0V
#2035000
1S
1V
#2040000
0S
0V
#2045000
1S
1V
#2050000
0S
0V
#2055000
1S
1V
#2060000
0S
0V
#2065000
1S
1V
#2070000
0S
0V
#2075000
1S
1V
#2080000
0S
0V
#2085000
1S
1V
#2090000
0S
0V
#2095000
1S
1V
#2100000
0S
0V
#2105000
1S
1V
#2110000
0S
0V
#2115000
1S
1V
#2120000
0S
0V
#2125000
1S
1V
#2130000
0S
0V
#2135000
1S
1V
#2140000
0S
0V
#2145000
1S
1V
#2150000
0S
0V
#2155000
1S
1V
#2160000
0S
0V
#2165000
1S
1V
#2170000
0S
0V
#2175000
1S
1U
1V
#2180000
0S
0V
#2185000
1S
0U
1V
#2190000
0S
0V
#2195000
1S
1V
#2200000
0S
0V
#2205000
1S
1V
#2210000
0S
0V
#2215000
1S
1V
#2220000
0S
0V
#2225000
1S
1V
14
1?
1=
1;
19
07
1G
1E
1C
1A
0P
#2230000
0S
0V
#2235000
1S
1V
04
06
17
1O
1M
1K
1I
1P
#2240000
0S
0V
#2245000
1S
1V
#2250000
0S
0V
#2255000
1S
1V
#2260000
0S
0V
#2265000
1S
1V
#2270000
0S
0V
#2275000
1S
1V
#2280000
0S
0V
#2285000
1S
1V
#2290000
0S
0V
#2295000
1S
1V
#2300000
0S
0V
#2305000
1S
1V
#2310000
0S
0V
#2315000
1S
1V
#2320000
0S
0V
#2325000
1S
1V
#2330000
0S
0V
#2335000
1S
1U
1V
#2340000
0S
0V
#2345000
1S
0U
1V
05
#2350000
0S
0V
#2355000
1S
1V
#2360000
0S
0V
#2365000
1S
1V
#2370000
0S
0V
#2375000
1S
1V
#2380000
0S
0V
#2385000
1S
1V
#2390000
0S
0V
#2395000
1S
1V
#2400000
0S
0V
#2405000
1S
1V
#2410000
0S
0V
#2415000
1S
1V
#2420000
0S
0V
#2425000
1S
1V
#2430000
0S
0V
#2435000
1S
1V
#2440000
0S
0V
#2445000
1S
1V
#2450000
0S
0V
#2455000
1S
1V
#2460000
0S
0V
#2465000
1S
1V
#2470000
0S
0V
#2475000
1S
1V
#2480000
0S
0V
#2485000
1S
1V
#2490000
0S
0V
#2495000
1S
1U
1V
#2500000
0S
0V
#2505000
1S
0U
1V
15
0Q
#2510000
0S
0V
#2515000
1S
1V
#2520000
0S
0V
#2525000
1S
1V
#2530000
0S
0V
#2535000
1S
1V
#2540000
0S
0V
#2545000
1S
1V
#2550000
0S
0V
#2555000
1S
1V
#2560000
0S
0V
#2565000
1S
1V
#2570000
0S
0V
#2575000
1S
1V
#2580000
0S
0V
#2585000
1S
1V
#2590000
0S
0V
#2595000
1S
1V
#2600000
0S
0V
#2605000
1S
1V
#2610000
0S
0V
#2615000
1S
1V
#2620000
0S
0V
#2625000
1S
1V
#2630000
0S
0V
#2635000
1S
1V
#2640000
0S
0V
#2645000
1S
1V
#2650000
0S
0V
#2655000
1S
1U
1V
#2660000
0S
0V
#2665000
1S
0U
1V
1Q
#2670000
0S
0V
#2675000
1S
1V
#2680000
0S
0V
#2685000
1S
1V
#2690000
0S
0V
#2695000
1S
1V
#2700000
0S
0V
#2705000
1S
1V
#2710000
0S
0V
#2715000
1S
1V
#2720000
0S
0V
#2725000
1S
1V
#2730000
0S
0V
#2735000
1S
1V
#2740000
0S
0V
#2745000
1S
1V
#2750000
0S
0V
#2755000
1S
1V
#2760000
0S
0V
#2765000
1S
1V
#2770000
0S
0V
#2775000
1S
1V
#2780000
0S
0V
#2785000
1S
1V
#2790000
0S
0V
#2795000
1S
1V
#2800000
0S
0V
#2805000
1S
1V
#2810000
0S
0V
#2815000
1S
1U
1V
#2820000
0S
0V
#2825000
1S
0U
1V
0Q
#2830000
0S
0V
#2835000
1S
1V
#2840000
0S
0V
#2845000
1S
1V
#2850000
0S
0V
#2855000
1S
1V
#2860000
0S
0V
#2865000
1S
1V
#2870000
0S
0V
#2875000
1S
1V
#2880000
0S
0V
#2885000
1S
1V
#2890000
0S
0V
#2895000
1S
1V
#2900000
0S
0V
#2905000
1S
1V
#2910000
0S
0V
#2915000
1S
1V
#2920000
0S
0V
#2925000
1S
1V
#2930000
0S
0V
#2935000
1S
1V
#2940000
0S
0V
#2945000
1S
1V
#2950000
0S
0V
#2955000
1S
1V
#2960000
0S
0V
#2965000
1S
1V
#2970000
0S
0V
#2975000
1S
1U
1V
#2980000
0S
0V
#2985000
1S
0U
1V
1Q
#2990000
0S
0V
#2995000
1S
1V
#3000000
0S
0V
#3005000
1S
1V
#3010000
0S
0V
#3015000
1S
1V
#3020000
0S
0V
#3025000
1S
1V
#3030000
0S
0V
#3035000
1S
1V
#3040000
0S
0V
#3045000
1S
1V
#3050000
0S
0V
#3055000
1S
1V
#3060000
0S
0V
#3065000
1S
1V
#3070000
0S
0V
#3075000
1S
1V
#3080000
0S
0V
#3085000
1S
1V
#3090000
0S
0V
#3095000
1S
1V
#3100000
0S
0V
#3105000
1S
1V
#3110000
0S
0V
#3115000
1S
1V
#3120000
0S
0V
#3125000
1S
1V
#3130000
0S
0V
#3135000
1S
1U
1V
#3140000
0S
0V
#3145000
1S
0U
1V
0Q
#3150000
0S
0V
#3155000
1S
1V
#3160000
0S
0V
#3165000
1S
1V
#3170000
0S
0V
#3175000
1S
1V
#3180000
0S
0V
#3185000
1S
1V
#3190000
0S
0V
#3195000
1S
1V
#3200000
0S
0V
#3205000
1S
1V
#3210000
0S
0V
#3215000
1S
1V
#3220000
0S
0V
#3225000
1S
1V
#3230000
0S
0V
#3235000
1S
1V
14
0?
0>
0=
0<
0;
0:
09
07
0G
0F
0E
0D
0C
0B
0A
0P
#3240000
0S
0V
#3245000
1S
1V
04
#3250000
0S
0V
#3255000
1S
1V
#3260000
0S
0V
#3265000
1S
1V
#3270000
0S
0V
#3275000
1S
1V
#3280000
0S
0V
#3285000
1S
1V
#3290000
0S
0V
#3295000
1S
1U
1V
#3300000
0S
0V
#3305000
1S
0U
1V
1Q
#3310000
0S
0V
#3315000
1S
1V
#3320000
0S
0V
#3325000
1S
1V
#3330000
0S
0V
#3335000
1S
1V
#3340000
0S
0V
#3345000
1S
1V
#3350000
0S
0V
#3355000
1S
1V
#3360000
0S
0V
#3365000
1S
1V
#3370000
0S
0V
#3375000
1S
1V
#3380000
0S
0V
#3385000
1S
1V
#3390000
0S
0V
#3395000
1S
1V
#3400000
0S
0V
#3405000
1S
1V
#3410000
0S
0V
#3415000
1S
1V
#3420000
0S
0V
#3425000
1S
1V
#3430000
0S
0V
#3435000
1S
1V
#3440000
0S
0V
#3445000
1S
1V
#3450000
0S
0V
#3455000
1S
1U
1V
#3460000
0S
0V
#3465000
1S
0U
1V
0Q
#3470000
0S
0V
#3475000
1S
1V
#3480000
0S
0V
#3485000
1S
1V
#3490000
0S
0V
#3495000
1S
1V
#3500000
0S
0V
#3505000
1S
1V
#3510000
0S
0V
#3515000
1S
1V
#3520000
0S
0V
#3525000
1S
1V
#3530000
0S
0V
#3535000
1S
1V
#3540000
0S
0V
#3545000
1S
1V
#3550000
0S
0V
#3555000
1S
1V
#3560000
0S
0V
#3565000
1S
1V
#3570000
0S
0V
#3575000
1S
1V
#3580000
0S
0V
#3585000
1S
1V
#3590000
0S
0V
#3595000
1S
1V
#3600000
0S
0V
#3605000
1S
1V
#3610000
0S
0V
#3615000
1S
1U
1V
#3620000
0S
0V
#3625000
1S
0U
1V
1Q
#3630000
0S
0V
#3635000
1S
1V
#3640000
0S
0V
#3645000
1S
1V
#3650000
0S
0V
#3655000
1S
1V
#3660000
0S
0V
#3665000
1S
1V
#3670000
0S
0V
#3675000
1S
1V
#3680000
0S
0V
#3685000
1S
1V
#3690000
0S
0V
#3695000
1S
1V
#3700000
0S
0V
#3705000
1S
1V
#3710000
0S
0V
#3715000
1S
1V
#3720000
0S
0V
#3725000
1S
1V
#3730000
0S
0V
#3735000
1S
1V
#3740000
0S
0V
#3745000
1S
1V
#3750000
0S
0V
#3755000
1S
1V
#3760000
0S
0V
#3765000
1S
1V
#3770000
0S
0V
#3775000
1S
1U
1V
#3780000
0S
0V
#3785000
1S
0U
1V
#3790000
0S
0V
#3795000
1S
1V
16
#3800000
0S
0V
#3805000
1S
1V
#3810000
0S
0V
#3815000
1S
1V
#3820000
0S
0V
#3825000
1S
1V
#3830000
0S
0V
#3835000
1S
1V
#3840000
0S
0V
#3845000
1S
1V
#3850000
0S
0V
#3855000
1S
1V
#3860000
0S
0V
#3865000
1S
1V
#3870000
0S
0V
#3875000
1S
1V
#3880000
0S
0V
#3885000
1S
1V
#3890000
0S
0V
#3895000
1S
1V
#3900000
0S
0V
#3905000
1S
1V
#3910000
0S
0V
#3915000
1S
1V
#3920000
0S
0V
#3925000
1S
1V
#3930000
0S
0V
#3935000
1S
1U
1V
#3940000
0S
0V
#3945000
1S
0U
1V
#3950000
0S
0V
#3955000
1S
1V
06
17
0O
0N
0M
0L
0K
0J
0I
1P
#3960000
0S
0V
#3965000
1S
1V
#3970000
0S
0V
#3975000
1S
1V
#3980000
0S
0V
#3985000
1S
1V
#3990000
0S
0V
#3995000
1S
1V
#4000000
0S
0V
#4005000
1S
1V
#4010000
0S
0V
#4015000
1S
1V
#4020000
0S
0V
#4025000
1S
1V
#4030000
0S
0V
#4035000
1S
1V
#4040000
0S
0V
#4045000
1S
1V
#4050000
0S
0V
#4055000
1S
1V
#4060000
0S
0V
#4065000
1S
1V
#4070000
0S
0V
#4075000
1S
1V
#4080000
0S
0V
#4085000
1S
1V
#4090000
0S
0V
#4095000
1S
1U
1V
#4100000
0S
0V
#4105000
1S
0U
1V
05
#4110000
0S
0V
#4115000
1S
1V
#4120000
0S
0V
#4125000
1S
1V
#4130000
0S
0V
#4135000
1S
1V
#4140000
0S
0V
#4145000
1S
1V
#4150000
0S
0V
#4155000
1S
1V
#4160000
0S
0V
#4165000
1S
1V
#4170000
0S
0V
#4175000
1S
1V
#4180000
0S
0V
#4185000
1S
1V
#4190000
0S
0V
#4195000
1S
1V
#4200000
0S
0V
#4205000
1S
1V
#4210000
0S
0V
#4215000
1S
1V
#4220000
0S
0V
#4225000
1S
1V
#4230000
0S
0V
#4235000
1S
1V
#4240000
0S
0V
#4245000
1S
1V
#4250000
0S
0V
#4255000
1S
1U
1V
#4260000
0S
0V
#4265000
1S
0U
1V
#4270000
0S
0V
#4275000
1S
1V
#4280000
0S
0V
#4285000
1S
1V
#4290000
0S
0V
#4295000
1S
1V
#4300000
0S
0V
#4305000
1S
1V
#4310000
0S
0V
#4315000
1S
1V
#4320000
0S
0V
#4325000
1S
1V
#4330000
0S
0V
#4335000
1S
1V
#4340000
0S
0V
#4345000
1S
1V
#4350000
0S
0V
#4355000
1S
1V
#4360000
0S
0V
#4365000
1S
1V
#4370000
0S
0V
#4375000
1S
1V
#4380000
0S
0V
#4385000
1S
1V
#4390000
0S
0V
#4395000
1S
1V
#4400000
0S
0V
#4405000
1S
1V
#4410000
0S
0V
#4415000
1S
1U
1V
#4420000
0S
0V
#4425000
1S
0U
1V
#4430000
0S
0V
#4435000
1S
1V
#4440000
0S
0V
#4445000
1S
1V
#4450000
0S
0V
#4455000
1S
1V
#4460000
0S
0V
#4465000
1S
1V
#4470000
0S
0V
#4475000
1S
1V
#4480000
0S
0V
#4485000
1S
1V
#4490000
0S
0V
#4495000
1S
1V
#4500000
0S
0V
#4505000
1S
1V
#4510000
0S
0V
#4515000
1S
1V
#4520000
0S
0V
#4525000
1S
1V
#4530000
0S
0V
#4535000
1S
1V
#4540000
0S
0V
#4545000
1S
1V
#4550000
0S
0V
#4555000
1S
1V
#4560000
0S
0V
#4565000
1S
1V
#4570000
0S
0V
#4575000
1S
1U
1V
#4580000
0S
0V
#4585000
1S
0U
1V
#4590000
0S
0V
#4595000
1S
1V
#4600000
0S
0V
#4605000
1S
1V
#4610000
0S
0V
#4615000
1S
1V
#4620000
0S
0V
#4625000
1S
1V
#4630000
0S
0V
#4635000
1S
1V
#4640000
0S
0V
#4645000
1S
1V
#4650000
0S
0V
#4655000
1S
1V
#4660000
0S
0V
#4665000
1S
1V
#4670000
0S
0V
#4675000
1S
1V
#4680000
0S
0V
#4685000
1S
1V
#4690000
0S
0V
#4695000
1S
1V
#4700000
0S
0V
#4705000
1S
1V
#4710000
0S
0V
#4715000
1S
1V
#4720000
0S
0V
#4725000
1S
1V
#4730000
0S
0V
#4735000
1S
1U
1V
#4740000
0S
0V
#4745000
1S
0U
1V
#4750000
0S
0V
#4755000
1S
1V
#4760000
0S
0V
#4765000
1S
1V
#4770000
0S
0V
#4775000
1S
1V
#4780000
0S
0V
#4785000
1S
1V
#4790000
0S
0V
#4795000
1S
1V
#4800000
0S
0V
#4805000
1S
1V
#4810000
0S
0V
#4815000
1S
1V
#4820000
0S
0V
#4825000
1S
1V
#4830000
0S
0V
#4835000
1S
1V
#4840000
0S
0V
#4845000
1S
1V
#4850000
0S
0V
#4855000
1S
1V
