clkUnit/clkUnit.vhd
library IEEE;
use IEEE.std_logic_1164.all;

entity clkUnit is
  
 port (
   clk, reset : in  std_logic;
   enableTX   : out std_logic;
   enableRX   : out std_logic);
    
end clkUnit;

architecture behavorial of clkUnit is
begin
  enableRX <= clk when reset = '1' else '0';

  process (clk, reset)
    variable cpt : integer;
  begin
    
    if reset = '0' then
      enableTX <= '0';
      cpt := 0;
    elsif rising_edge(clk) then  
      if cpt = 15 then
        enableTX <= '1';
        cpt := 0;
      else 
        enableTX <= '0';
        cpt := cpt + 1;
      end if;
    end if;
  end process;
end behavorial;

TxUnit/TxUnit.vhd
library IEEE;
use IEEE.std_logic_1164.all;

entity TxUnit is
  port (
    clk, reset : in std_logic;
    enable : in std_logic;
    ld : in std_logic;
    txd : out std_logic;
    regE : out std_logic;
    bufE : out std_logic;
    data : in std_logic_vector(7 downto 0));
end TxUnit;



architecture behavorial of TxUnit is
  -- Déclaration du tamppon et du registre d'emission
  signal bufferT, registerT : std_logic_vector(7 downto 0);
  -- Compteur de bit pour savoir si on est dans le cas du bit de start, des 8 bits d'emission, du bit de parité ou du bit de stop 
  signal cpt_bit : integer;
  signal bufE_signal : std_logic;
  -- Parité
  signal parite : std_logic := '0';
  --etat
  type t_etat is (repos,init,debut,transmission,fin);
  signal etat : t_etat;

begin
  bufE <= bufE_signal;
  process(clk,reset)
  begin 
    if reset = '0' then
      cpt_bit <= 0;
      txd <= '1';
      bufE_signal <= '1';
      etat <= repos;

    elsif rising_edge(clk) then 
        case etat is 

          when repos => 
            regE <= '1';
            if ld = '1' then 
              etat <= init;          
            end if;

          when init => 
            registerT <= bufferT;
            regE <= '0';
            bufE_signal <= '1';
            etat <= debut;

          when debut => 
            if enable = '1' then
              txd <= '0';
              cpt_bit <= 7;
              etat <= transmission;
            end if;

          when transmission => 
            
            if enable = '1' and cpt_bit > 0 then
              txd <= registerT(cpt_bit);
              cpt_bit <= cpt_bit - 1;
            elsif enable = '1' and cpt_bit = 0 then
              txd <= registerT(0);
              etat <= fin;
            end if;

          when fin => 

            if enable = '1' then
              txd <= '1';
              if bufE_signal = '0' then
                etat <= debut;
              elsif bufE_signal = '1' then
                etat <= repos;
              end if;
            end if;
      end case;

      if ld = '1' then
        bufferT <= data;
        bufE_signal <= '0';
      end if;
    end if;
  end process;
end behavorial;

TxUnit/testTxUnit.vhd
--------------------------------------------------------------------------------
-- Company: 
-- Engineer:
--
-- Create Date:   12:09:49 10/31/2018
-- Design Name:   
-- Module Name:   testTxUnit.vhd
-- Project Name:  uart
-- Target Device:  
-- Tool versions:  
-- Description:   
-- 
-- VHDL Test Bench Created by ISE for module: TxUnit
-- 
-- Dependencies:
-- 
-- Revision:
-- Revision 0.01 - File Created
-- Additional Comments:
--
-- Notes: 
-- This testbench has been automatically generated using types std_logic and
-- std_logic_vector for the ports of the unit under test.  Xilinx recommends
-- that these types always be used for the top-level I/O of a design in order
-- to guarantee that the testbench will bind correctly to the post-implementation 
-- simulation model.
--------------------------------------------------------------------------------
LIBRARY ieee;
USE ieee.std_logic_1164.ALL;
 
-- Uncomment the following library declaration if using
-- arithmetic functions with Signed or Unsigned values
--USE ieee.numeric_std.ALL;
 
ENTITY testTxUnit IS
END testTxUnit;
 
ARCHITECTURE behavior OF testTxUnit IS 
 
    -- Component Declaration for the Unit Under Test (UUT)
 
    COMPONENT TxUnit
    PORT(
         clk : IN  std_logic;
         reset : IN  std_logic;
         enable : IN  std_logic;
         ld : IN  std_logic;
         txd : OUT  std_logic;
         regE : OUT  std_logic;
         bufE : OUT  std_logic;
         data : IN  std_logic_vector(7 downto 0)
        );
    END COMPONENT;
   
    COMPONENT clkUnit
    PORT(
         clk : IN  std_logic;
         reset : IN  std_logic;
         enableTX : OUT  std_logic;
         enableRX : OUT  std_logic
        );
    END COMPONENT;	

   signal clk : std_logic := '0';
   signal reset : std_logic := '0';
   signal enableTx : std_logic := '0';
   signal enableRx : std_logic := '0';
   signal ld : std_logic := '0';
   signal data : std_logic_vector(7 downto 0) := (others => '0');

   signal txd : std_logic;
   signal regE : std_logic;
   signal bufE : std_logic;

   -- Clock period definitions
   constant clk_period : time := 10 ns;
 
BEGIN
 
	-- Instantiate the Unit Under Test
   uut0: TxUnit PORT MAP (
          clk => clk,
          reset => reset,
          enable => enableTX,
          ld => ld,
          txd => txd,
          regE => regE,
          bufE => bufE,
          data => data
        );

   -- Instantiate the clkUnit
   clkUnit1: clkUnit PORT MAP (
          clk => clk,
          reset => reset,
          enableTX => enableTX,
          enableRX => enableRX
        );
		  
   -- Clock process definitions
   clk_process :process
   begin
     clk <= '0';
     wait for clk_period/2;
     clk <= '1';
     wait for clk_period/2;
   end process;
 
 
   -- Stimulus process
   stim_proc: process
   begin		
     -- maintien du reset durant 100 ns.
     wait for 100 ns;	
     reset <= '1';

     wait for 200 ns;

     -- l'émetteur est dispo ?
     if not (regE='1' and bufE='1') then
       wait until regE='1' and bufE='1';
     end if;

     -- si oui, on charge la donnée
     wait for clk_period;
     -- émission du caractère 0x55
     data <= "01010101";
     ld <= '1';

     -- on attend de voir que l'ordre d'émission
     -- a été bien pris en compte avant de rabaisser
     -- le signal ld
     if not (regE='1' and bufE='0') then
       wait until regE='1' and bufE='0';
     end if;
     wait for clk_period;
     ld <= '0';

     -- compléter avec des tests qui montrent que la prise
     -- en compte de la demande d'émission d'un second
     -- caractère se fait lorsqu'on émet un premier caractère
     -- et ceci quelque soit l'étape d'émission
    
     -- si oui, on charge la donnée
     wait for clk_period*190;
     -- émission du caractère 0x55
     data <= "11111111";
     ld <= '1';
     
     -- on attend de voir que l'ordre d'émission
     -- a été bien pris en compte avant de rabaisser
     -- le signal ld
     if not (regE='1' and bufE='0') then
      wait until regE='1' and bufE='0';
    end if;
    wait for clk_period;
    ld <= '0';

    -- si oui, on charge la donnée
    wait for clk_period*100;
    -- émission du caractère 0x55
    data <= "00000001";
    ld <= '1';
    wait for clk_period;
    ld <= '0';

     wait;
   end process;

END;

TxUnit/output.vcd
$date
   Fri Dec 13 11:18:42 2024
$end
$version
  P.20131013
$end
$timescale
  1ps
$end
$scope module testtxunit $end
$var wire 1 T clk $end
$var wire 1 U reset $end
$var wire 1 V enabletx $end
$var wire 1 W enablerx $end
$var wire 1 4 ld $end
$var wire 1 ? data [7] $end
$var wire 1 > data [6] $end
$var wire 1 = data [5] $end
$var wire 1 < data [4] $end
$var wire 1 ; data [3] $end
$var wire 1 : data [2] $end
$var wire 1 9 data [1] $end
$var wire 1 8 data [0] $end
$var wire 1 5 txd $end
$var wire 1 6 rege $end
$var wire 1 7 bufe $end
$scope module uut0 $end
$var wire 1 T clk $end
$var wire 1 U reset $end
$var wire 1 V enable $end
$var wire 1 4 ld $end
$var wire 1 5 txd $end
$var wire 1 6 rege $end
$var wire 1 7 bufe $end
$var wire 1 ? data [7] $end
$var wire 1 > data [6] $end
$var wire 1 = data [5] $end
$var wire 1 < data [4] $end
$var wire 1 ; data [3] $end
$var wire 1 : data [2] $end
$var wire 1 9 data [1] $end
$var wire 1 8 data [0] $end
$var wire 1 G buffert [7] $end
$var wire 1 F buffert [6] $end
$var wire 1 E buffert [5] $end
$var wire 1 D buffert [4] $end
$var wire 1 C buffert [3] $end
$var wire 1 B buffert [2] $end
$var wire 1 A buffert [1] $end
$var wire 1 @ buffert [0] $end
$var wire 1 O registert [7] $end
$var wire 1 N registert [6] $end
$var wire 1 M registert [5] $end
$var wire 1 L registert [4] $end
$var wire 1 K registert [3] $end
$var wire 1 J registert [2] $end
$var wire 1 I registert [1] $end
$var wire 1 H registert [0] $end
$var wire 1 Q bufe_signal $end
$var wire 1 R parite $end
$upscope $end
$scope module clkUnit1 $end
$var wire 1 T clk $end
$var wire 1 U reset $end
$var wire 1 V enabletx $end
$var wire 1 W enablerx $end
$upscope $end
$upscope $end
$enddefinitions $end
#0
$dumpvars
0U
0T
0V
0W
04
0?
0>
0=
0<
0;
0:
09
08
15
x6
17
xG
xF
xE
xD
xC
xB
xA
x@
xO
xN
xM
xL
xK
xJ
xI
xH
1Q
0R
$end
#5000
1T
#10000
0T
#15000
1T
#20000
0T
#25000
1T
#30000
0T
#35000
1T
#40000
0T
#45000
1T
#50000
0T
#55000
1T
#60000
0T
#65000
1T
#70000
0T
#75000
1T
#80000
0T
#85000
1T
#90000
0T
#95000
1T
#100000
1U
0T
#105000
1T
1W
16
#110000
0T
0W
#115000
1T
1W
#120000
0T
0W
#125000
1T
1W
#130000
0T
0W
#135000
1T
1W
#140000
0T
0W
#145000
1T
1W
#150000
0T
0W
#155000
1T
1W
#160000
0T
0W
#165000
1T
1W
#170000
0T
0W
#175000
1T
1W
#180000
0T
0W
#185000
1T
1W
#190000
0T
0W
#195000
1T
1W
#200000
0T
0W
#205000
1T
1W
#210000
0T
0W
#215000
1T
1W
#220000
0T
0W
#225000
1T
1W
#230000
0T
0W
#235000
1T
1W
#240000
0T
0W
#245000
1T
1W
#250000
0T
0W
#255000
1T
1V
1W
#260000
0T
0W
#265000
1T
0V
1W
#270000
0T
0W
#275000
1T
1W
#280000
0T
0W
#285000
1T
1W
#290000
0T
0W
#295000
1T
1W
#300000
0T
0W
#305000
1T
1W
#310000
0T
0W
14
1>
1<
1:
18
#315000
1T
1W
07
0G
1F
0E
1D
0C
1B
0A
1@
0Q
#320000
0T
0W
#325000
1T
1W
04
06
17
0O
1N
0M
1L
0K
1J
0I
1H
1Q
#330000
0T
0W
#335000
1T
1W
#340000
0T
0W
#345000
1T
1W
#350000
0T
0W
#355000
1T
1W
#360000
0T
0W
#365000
1T
1W
#370000
0T
0W
#375000
1T
1W
#380000
0T
0W
#385000
1T
1W
#390000
0T
0W
#395000
1T
1W
#400000
0T
0W
#405000
1T
1W
#410000
0T
0W
#415000
1T
1V
1W
#420000
0T
0W
#425000
1T
0V
1W
05
#430000
0T
0W
#435000
1T
1W
#440000
0T
0W
#445000
1T
1W
#450000
0T
0W
#455000
1T
1W
#460000
0T
0W
#465000
1T
1W
#470000
0T
0W
#475000
1T
1W
#480000
0T
0W
#485000
1T
1W
#490000
0T
0W
#495000
1T
1W
#500000
0T
0W
#505000
1T
1W
#510000
0T
0W
#515000
1T
1W
#520000
0T
0W
#525000
1T
1W
#530000
0T
0W
#535000
1T
1W
#540000
0T
0W
#545000
1T
1W
#550000
0T
0W
#555000
1T
1W
#560000
0T
0W
#565000
1T
1W
#570000
0T
0W
#575000
1T
1V
1W
#580000
0T
0W
#585000
1T
0V
1W
#590000
0T
0W
#595000
1T
1W
#600000
0T
0W
#605000
1T
1W
#610000
0T
0W
#615000
1T
1W
#620000
0T
0W
#625000
1T
1W
#630000
0T
0W
#635000
1T
1W
#640000
0T
0W
#645000
1T
1W
#650000
0T
0W
#655000
1T
1W
#660000
0T
0W
#665000
1T
1W
#670000
0T
0W
#675000
1T
1W
#680000
0T
0W
#685000
1T
1W
#690000
0T
0W
#695000
1T
1W
#700000
0T
0W
#705000
1T
1W
#710000
0T
0W
#715000
1T
1W
#720000
0T
0W
#725000
1T
1W
#730000
0T
0W
#735000
1T
1V
1W
#740000
0T
0W
#745000
1T
0V
1W
15
#750000
0T
0W
#755000
1T
1W
#760000
0T
0W
#765000
1T
1W
#770000
0T
0W
#775000
1T
1W
#780000
0T
0W
#785000
1T
1W
#790000
0T
0W
#795000
1T
1W
#800000
0T
0W
#805000
1T
1W
#810000
0T
0W
#815000
1T
1W
#820000
0T
0W
#825000
1T
1W
#830000
0T
0W
#835000
1T
1W
#840000
0T
0W
#845000
1T
1W
#850000
0T
0W
#855000
1T
1W
#860000
0T
0W
#865000
1T
1W
#870000
0T
0W
#875000
1T
1W
#880000
0T
0W
#885000
1T
1W
#890000
0T
0W
#895000
1T
1V
1W
#900000
0T
0W
#905000
1T
0V
1W
05
#910000
0T
0W
#915000
1T
1W
#920000
0T
0W
#925000
1T
1W
#930000
0T
0W
#935000
1T
1W
#940000
0T
0W
#945000
1T
1W
#950000
0T
0W
#955000
1T
1W
#960000
0T
0W
#965000
1T
1W
#970000
0T
0W
#975000
1T
1W
#980000
0T
0W
#985000
1T
1W
#990000
0T
0W
#995000
1T
1W
#1000000
0T
0W
#1005000
1T
1W
#1010000
0T
0W
#1015000
1T
1W
#1020000
0T
0W
#1025000
1T
1W
#1030000
0T
0W
#1035000
1T
1W
#1040000
0T
0W
#1045000
1T
1W
#1050000
0T
0W
#1055000
1T
1V
1W
#1060000
0T
0W
#1065000
1T
0V
1W
15
#1070000
0T
0W
#1075000
1T
1W
#1080000
0T
0W
#1085000
1T
1W
#1090000
0T
0W
#1095000
1T
1W
#1100000
0T
0W
#1105000
1T
1W
#1110000
0T
0W
#1115000
1T
1W
#1120000
0T
0W
#1125000
1T
1W
#1130000
0T
0W
#1135000
1T
1W
#1140000
0T
0W
#1145000
1T
1W
#1150000
0T
0W
#1155000
1T
1W
#1160000
0T
0W
#1165000
1T
1W
#1170000
0T
0W
#1175000
1T
1W
#1180000
0T
0W
#1185000
1T
1W
#1190000
0T
0W
#1195000
1T
1W
#1200000
0T
0W
#1205000
1T
1W
#1210000
0T
0W
#1215000
1T
1V
1W
#1220000
0T
0W
#1225000
1T
0V
1W
05
#1230000
0T
0W
#1235000
1T
1W
#1240000
0T
0W
#1245000
1T
1W
#1250000
0T
0W
#1255000
1T
1W
#1260000
0T
0W
#1265000
1T
1W
#1270000
0T
0W
#1275000
1T
1W
#1280000
0T
0W
#1285000
1T
1W
#1290000
0T
0W
#1295000
1T
1W
#1300000
0T
0W
#1305000
1T
1W
#1310000
0T
0W
#1315000
1T
1W
#1320000
0T
0W
#1325000
1T
1W
#1330000
0T
0W
#1335000
1T
1W
#1340000
0T
0W
#1345000
1T
1W
#1350000
0T
0W
#1355000
1T
1W
#1360000
0T
0W
#1365000
1T
1W
#1370000
0T
0W
#1375000
1T
1V
1W
#1380000
0T
0W
#1385000
1T
0V
1W
15
#1390000
0T
0W
#1395000
1T
1W
#1400000
0T
0W
#1405000
1T
1W
#1410000
0T
0W
#1415000
1T
1W
#1420000
0T
0W
#1425000
1T
1W
#1430000
0T
0W
#1435000
1T
1W
#1440000
0T
0W
#1445000
1T
1W
#1450000
0T
0W
#1455000
1T
1W
#1460000
0T
0W
#1465000
1T
1W
#1470000
0T
0W
#1475000
1T
1W
#1480000
0T
0W
#1485000
1T
1W
#1490000
0T
0W
#1495000
1T
1W
#1500000
0T
0W
#1505000
1T
1W
#1510000
0T
0W
#1515000
1T
1W
#1520000
0T
0W
#1525000
1T
1W
#1530000
0T
0W
#1535000
1T
1V
1W
#1540000
0T
0W
#1545000
1T
0V
1W
05
#1550000
0T
0W
#1555000
1T
1W
#1560000
0T
0W
#1565000
1T
1W
#1570000
0T
0W
#1575000
1T
1W
#1580000
0T
0W
#1585000
1T
1W
#1590000
0T
0W
#1595000
1T
1W
#1600000
0T
0W
#1605000
1T
1W
#1610000
0T
0W
#1615000
1T
1W
#1620000
0T
0W
#1625000
1T
1W
#1630000
0T
0W
#1635000
1T
1W
#1640000
0T
0W
#1645000
1T
1W
#1650000
0T
0W
#1655000
1T
1W
#1660000
0T
0W
#1665000
1T
1W
#1670000
0T
0W
#1675000
1T
1W
#1680000
0T
0W
#1685000
1T
1W
#1690000
0T
0W
#1695000
1T
1V
1W
#1700000
0T
0W
#1705000
1T
0V
1W
15
#1710000
0T
0W
#1715000
1T
1W
#1720000
0T
0W
#1725000
1T
1W
#1730000
0T
0W
#1735000
1T
1W
#1740000
0T
0W
#1745000
1T
1W
#1750000
0T
0W
#1755000
1T
1W
#1760000
0T
0W
#1765000
1T
1W
#1770000
0T
0W
#1775000
1T
1W
#1780000
0T
0W
#1785000
1T
1W
#1790000
0T
0W
#1795000
1T
1W
#1800000
0T
0W
#1805000
1T
1W
#1810000
0T
0W
#1815000
1T
1W
#1820000
0T
0W
#1825000
1T
1W
#1830000
0T
0W
#1835000
1T
1W
#1840000
0T
0W
#1845000
1T
1W
#1850000
0T
0W
#1855000
1T
1V
1W
#1860000
0T
0W
#1865000
1T
0V
1W
#1870000
0T
0W
#1875000
1T
1W
16
#1880000
0T
0W
#1885000
1T
1W
#1890000
0T
0W
#1895000
1T
1W
#1900000
0T
0W
#1905000
1T
1W
#1910000
0T
0W
#1915000
1T
1W
#1920000
0T
0W
#1925000
1T
1W
#1930000
0T
0W
#1935000
1T
1W
#1940000
0T
0W
#1945000
1T
1W
#1950000
0T
0W
#1955000
1T
1W
#1960000
0T
0W
#1965000
1T
1W
#1970000
0T
0W
#1975000
1T
1W
#1980000
0T
0W
#1985000
1T
1W
#1990000
0T
0W
#1995000
1T
1W
#2000000
0T
0W
#2005000
1T
1W
#2010000
0T
0W
#2015000
1T
1V
1W
#2020000
0T
0W
#2025000
1T
0V
1W
#2030000
0T
0W
#2035000
1T
1W
#2040000
0T
0W
#2045000
1T
1W
#2050000
0T
0W
#2055000
1T
1W
#2060000
0T
0W
#2065000
1T
1W
#2070000
0T
0W
#2075000
1T
1W
#2080000
0T
0W
#2085000
1T
1W
#2090000
0T
0W
#2095000
1T
1W
#2100000
0T
0W
#2105000
1T
1W
#2110000
0T
0W
#2115000
1T
1W
#2120000
0T
0W
#2125000
1T
1W
#2130000
0T
0W
#2135000
1T
1W
#2140000
0T
0W
#2145000
1T
1W
#2150000
0T
0W
#2155000
1T
1W
#2160000
0T
0W
#2165000
1T
1W
#2170000
0T
0W
#2175000
1T
1V
1W
#2180000
0T
0W
#2185000
1T
0V
1W
#2190000
0T
0W
#2195000
1T
1W
#2200000
0T
0W
#2205000
1T
1W
#2210000
0T
0W
#2215000
1T
1W
#2220000
0T
0W
#2225000
1T
1W
#2230000
0T
0W
#2235000
1T
1W
#2240000
0T
0W
#2245000
1T
1W
#2250000
0T
0W
#2255000
1T
1W
#2260000
0T
0W
#2265000
1T
1W
#2270000
0T
0W
#2275000
1T
1W
#2280000
0T
0W
#2285000
1T
1W
#2290000
0T
0W
#2295000
1T
1W
#2300000
0T
0W
#2305000
1T
1W
#2310000
0T
0W
#2315000
1T
1W
#2320000
0T
0W
#2325000
1T
1W
#2330000
0T
0W
#2335000
1T
1V
1W
#2340000
0T
0W
#2345000
1T
0V
1W
#2350000
0T
0W
#2355000
1T
1W
#2360000
0T
0W
#2365000
1T
1W
#2370000
0T
0W
#2375000
1T
1W
#2380000
0T
0W
#2385000
1T
1W
#2390000
0T
0W
#2395000
1T
1W
#2400000
0T
0W
#2405000
1T
1W
#2410000
0T
0W
#2415000
1T
1W
#2420000
0T
0W
#2425000
1T
1W
#2430000
0T
0W
#2435000
1T
1W
#2440000
0T
0W
#2445000
1T
1W
#2450000
0T
0W
#2455000
1T
1W
#2460000
0T
0W
#2465000
1T
1W
#2470000
0T
0W
#2475000
1T
1W
#2480000
0T
0W
#2485000
1T
1W
#2490000
0T
0W
#2495000
1T
1V
1W
#2500000
0T
0W
#2505000
1T
0V
1W
#2510000
0T
0W
#2515000
1T
1W
#2520000
0T
0W
#2525000
1T
1W
#2530000
0T
0W
#2535000
1T
1W
#2540000
0T
0W
#2545000
1T
1W
#2550000
0T
0W
#2555000
1T
1W
#2560000
0T
0W
#2565000
1T
1W
#2570000
0T
0W
#2575000
1T
1W
#2580000
0T
0W
#2585000
1T
1W
#2590000
0T
0W
#2595000
1T
1W
#2600000
0T
0W
#2605000
1T
1W
#2610000
0T
0W
#2615000
1T
1W
#2620000
0T
0W
#2625000
1T
1W
#2630000
0T
0W
#2635000
1T
1W
#2640000
0T
0W
#2645000
1T
1W
#2650000
0T
0W
#2655000
1T
1V
1W
#2660000
0T
0W
#2665000
1T
0V
1W
#2670000
0T
0W
#2675000
1T
1W
#2680000
0T
0W
#2685000
1T
1W
#2690000
0T
0W
#2695000
1T
1W
#2700000
0T
0W
#2705000
1T
1W
#2710000
0T
0W
#2715000
1T
1W
#2720000
0T
0W
#2725000
1T
1W
#2730000
0T
0W
#2735000
1T
1W
#2740000
0T
0W
#2745000
1T
1W
#2750000
0T
0W
#2755000
1T
1W
#2760000
0T
0W
#2765000
1T
1W
#2770000
0T
0W
#2775000
1T
1W
#2780000
0T
0W
#2785000
1T
1W
#2790000
0T
0W
#2795000
1T
1W
#2800000
0T
0W
#2805000
1T
1W
#2810000
0T
0W
#2815000
1T
1V
1W
#2820000
0T
0W
#2825000
1T
0V
1W
#2830000
0T
0W
#2835000
1T
1W
#2840000
0T
0W
#2845000
1T
1W
#2850000
0T
0W
#2855000
1T
1W
#2860000
0T
0W
#2865000
1T
1W
#2870000
0T
0W
#2875000
1T
1W
#2880000
0T
0W
#2885000
1T
1W
#2890000
0T
0W
#2895000
1T
1W
#2900000
0T
0W
#2905000
1T
1W
#2910000
0T
0W
#2915000
1T
1W
#2920000
0T
0W
#2925000
1T
1W
#2930000
0T
0W
#2935000
1T
1W
#2940000
0T
0W
#2945000
1T
1W
#2950000
0T
0W
#2955000
1T
1W
#2960000
0T
0W
#2965000
1T
1W
#2970000
0T
0W
#2975000
1T
1V
1W
#2980000
0T
0W
#2985000
1T
0V
1W
#2990000
0T
0W
#2995000
1T
1W
#3000000
0T
0W
#3005000
1T
1W
#3010000
0T
0W
#3015000
1T
1W
#3020000
0T
0W
#3025000
1T
1W
#3030000
0T
0W
#3035000
1T
1W
#3040000
0T
0W
#3045000
1T
1W
#3050000
0T
0W
#3055000
1T
1W
#3060000
0T
0W
#3065000
1T
1W
#3070000
0T
0W
#3075000
1T
1W
#3080000
0T
0W
#3085000
1T
1W
#3090000
0T
0W
#3095000
1T
1W
#3100000
0T
0W
#3105000
1T
1W
#3110000
0T
0W
#3115000
1T
1W
#3120000
0T
0W
#3125000
1T
1W
#3130000
0T
0W
#3135000
1T
1V
1W
#3140000
0T
0W
#3145000
1T
0V
1W
#3150000
0T
0W
#3155000
1T
1W
#3160000
0T
0W
#3165000
1T
1W
#3170000
0T
0W
#3175000
1T
1W
#3180000
0T
0W
#3185000
1T
1W
#3190000
0T
0W
#3195000
1T
1W
#3200000
0T
0W
#3205000
1T
1W
#3210000
0T
0W
#3215000
1T
1W
#3220000
0T
0W
#3225000
1T
1W
#3230000
0T
0W
#3235000
1T
1W
#3240000
0T
0W
#3245000
1T
1W
#3250000
0T
0W
#3255000
1T
1W
#3260000
0T
0W
#3265000
1T
1W
#3270000
0T
0W
#3275000
1T
1W
#3280000
0T
0W
#3285000
1T
1W
#3290000
0T
0W
#3295000
1T
1V
1W
#3300000
0T
0W
#3305000
1T
0V
1W
#3310000
0T
0W
#3315000
1T
1W
#3320000
0T
0W
#3325000
1T
1W
#3330000
0T
0W
#3335000
1T
1W
#3340000
0T
0W
#3345000
1T
1W
#3350000
0T
0W
#3355000
1T
1W
#3360000
0T
0W
#3365000
1T
1W
#3370000
0T
0W
#3375000
1T
1W
#3380000
0T
0W
#3385000
1T
1W
#3390000
0T
0W
#3395000
1T
1W
#3400000
0T
0W
#3405000
1T
1W
#3410000
0T
0W
#3415000
1T
1W
#3420000
0T
0W
#3425000
1T
1W
#3430000
0T
0W
#3435000
1T
1W
#3440000
0T
0W
#3445000
1T
1W
#3450000
0T
0W
#3455000
1T
1V
1W
#3460000
0T
0W
#3465000
1T
0V
1W
#3470000
0T
0W
#3475000
1T
1W
#3480000
0T
0W
#3485000
1T
1W
#3490000
0T
0W
#3495000
1T
1W
#3500000
0T
0W
#3505000
1T
1W
#3510000
0T
0W
#3515000
1T
1W
#3520000
0T
0W
#3525000
1T
1W
#3530000
0T
0W
#3535000
1T
1W
#3540000
0T
0W
#3545000
1T
1W
#3550000
0T
0W
#3555000
1T
1W
#3560000
0T
0W
#3565000
1T
1W
#3570000
0T
0W
#3575000
1T
1W
#3580000
0T
0W
#3585000
1T
1W
#3590000
0T
0W
#3595000
1T
1W
#3600000
0T
0W
#3605000
1T
1W
#3610000
0T
0W
#3615000
1T
1V
1W
#3620000
0T
0W
#3625000
1T
0V
1W
#3630000
0T
0W
#3635000
1T
1W
#3640000
0T
0W
#3645000
1T
1W
#3650000
0T
0W
#3655000
1T
1W
#3660000
0T
0W
#3665000
1T
1W
#3670000
0T
0W
#3675000
1T
1W
#3680000
0T
0W
#3685000
1T
1W
#3690000
0T
0W
#3695000
1T
1W
#3700000
0T
0W
#3705000
1T
1W
#3710000
0T
0W
#3715000
1T
1W
#3720000
0T
0W
#3725000
1T
1W
#3730000
0T
0W
#3735000
1T
1W
#3740000
0T
0W
#3745000
1T
1W
#3750000
0T
0W
#3755000
1T
1W
#3760000
0T
0W
#3765000
1T
1W
#3770000
0T
0W
#3775000
1T
1V
1W
#3780000
0T
0W
#3785000
1T
0V
1W
#3790000
0T
0W
#3795000
1T
1W
#3800000
0T
0W
#3805000
1T
1W
#3810000
0T
0W
#3815000
1T
1W
#3820000
0T
0W
#3825000
1T
1W
#3830000
0T
0W
#3835000
1T
1W
#3840000
0T
0W
#3845000
1T
1W
#3850000
0T
0W
#3855000
1T
1W
#3860000
0T
0W
#3865000
1T
1W
#3870000
0T
0W
#3875000
1T
1W
#3880000
0T
0W
#3885000
1T
1W
#3890000
0T
0W
#3895000
1T
1W
#3900000
0T
0W
#3905000
1T
1W
#3910000
0T
0W
#3915000
1T
1W
#3920000
0T
0W
#3925000
1T
1W
#3930000
0T
0W
#3935000
1T
1V
1W
#3940000
0T
0W
#3945000
1T
0V
1W
#3950000
0T
0W
#3955000
1T
1W
#3960000
0T
0W
#3965000
1T
1W
#3970000
0T
0W
#3975000
1T
1W
#3980000
0T
0W
#3985000
1T
1W
#3990000
0T
0W
#3995000
1T
1W
#4000000
0T
0W
